Workbook

Sheet Cover Page
B2: DEEPGRID SEMI PRIVATE LIMITED
B3: India's First Full-Stack ADAS Company — Built on Its Own Transformer Silicon
B4: Business Plan & Financial Model · Pre-Series A · June 2026
B8: THE OPPORTUNITY | F8: FY2032 PROJECTIONS
B9: Instrument | C9: Equity / Compulsorily Convertible | F9: REVENUE | G9: EBITDA
B10: Raise target | C10: USD $4.0 – 5.0M (≈ ₹45 Cr) | F10: ='P&L'!I6 -> 1387.95 | G10: ='P&L'!I19 -> 536.62825
B11: Stage | C11: Pre-Series A | F11: ₹ Cr · FY2032E | G11: ₹ Cr · ~39% margin
B12: Key use | C12: SoC2 28nm tapeout → ASIC scale
B13: Allocation | C13: ~80% silicon & tapeout · balance GTM | F13: NET INCOME | G13: GROSS MARGIN
F14: ='P&L'!I31 -> 381.37069 | G14: ='P&L'!P8 -> 0.88364891
F15: ₹ Cr · FY2032E | G15: FY2032E
B17: SIX-YEAR FINANCIAL SUMMARY (₹ Crore)
C18: FY2027 | D18: FY2028 | E18: FY2029 | F18: FY2030 | G18: FY2031 | H18: FY2032
B19: Revenue | C19: ='P&L'!D6 -> 5.995 | D19: ='P&L'!E6 -> 41.166 | E19: ='P&L'!F6 -> 144.7275 | F19: ='P&L'!G6 -> 351.355 | G19: ='P&L'!H6 -> 731.545 | H19: ='P&L'!I6 -> 1387.95
B20: EBITDA | C20: ='P&L'!D19 -> -1.7999053 | D20: ='P&L'!E19 -> 2.5935518 | E20: ='P&L'!F19 -> 29.732762 | F20: ='P&L'!G19 -> 96.494524 | G20: ='P&L'!H19 -> 240.91366 | H20: ='P&L'!I19 -> 536.62825
B21: Net income | C21: ='P&L'!D31 -> -2.2948053 | D21: ='P&L'!E31 -> -0.67468013 | E21: ='P&L'!F31 -> 19.847409 | F21: ='P&L'!G31 -> 66.819318 | G21: ='P&L'!H31 -> 169.43082 | H21: ='P&L'!I31 -> 381.37069
B23: WORKBOOK CONTENTS
B24: Finanacial Overview | F24: Working
B25: P&L | C25: Projected income statement, FY27–FY32 | F25: Market | G25: TAM, mandate & competitive pricing
B26: Sales Summary | C26: Revenue by line, category & model | F26: Assumptions | G26: Margins, opex ratios, FX
B27: Use of Funds | C27: Sources & uses of the round | F27: Revenue Master | G27: Bottom-up build — 26 product lines
B28: Historical Context | C28: Prior-year background | F28: Tapeout Expenses | G28: SoC2 28nm NRE & mask phasing
B29: CGTMSE Debt | C29: Non-dilutive working-capital facility | F29: Payroll | G29: Headcount & fully-loaded people cost
B30: Cap Table | C30: Shareholding pre-round | F30: Expense Schedules | G30: Non-payroll R&D / S&M / G&A detail
B33: STRICTLY CONFIDENTIAL — This financial model is furnished through Emani Capital Advisory Pvt Ltd solely for the evaluation of the proposed Pre-Series A investment. It may not be reproduced or distributed without prior written consent. Figures are management projections, not audited, and subject to the assumptions set out herein. Contact: Haradatta Emani · haradatta@emanicapital.com · +91 98496 53907

Sheet Financial Overview>>

Sheet P&L
B2: DeepGrid Semi Private Limited
B3: Projected Income Statement
B5: Line Item | C5: x | D5: FY2027 | E5: FY2028 | F5: FY2029 | G5: FY2030 | H5: FY2031 | I5: FY2032 | J5: x | K5: FY2027 | L5: FY2028 | M5: FY2029 | N5: FY2030 | O5: FY2031 | P5: FY2032 | Q5: x | R5: Comments
B6: Revenue | D6: ='Revenue Master'!I34 -> 5.995 | E6: ='Revenue Master'!J34 -> 41.166 | F6: ='Revenue Master'!K34 -> 144.7275 | G6: ='Revenue Master'!L34 -> 351.355 | H6: ='Revenue Master'!M34 -> 731.545 | I6: ='Revenue Master'!N34 -> 1387.95 | K6: =D6/D6 -> 1 | L6: =E6/E6 -> 1 | M6: =F6/F6 -> 1 | N6: =G6/G6 -> 1 | O6: =H6/H6 -> 1 | P6: =I6/I6 -> 1 | R6: Built bottom-up from 26 individual product lines (see Revenue Master) — unit volumes × ASPs by SKU, not top-down market-share assumptions. Reflects the FPGA-pilot-to-ASIC-volume transition from FY2027.
B7: COGS | D7: =Assumptions!D21 -> 2.7915 | E7: =Assumptions!E21 -> 10.80288 | F7: =Assumptions!F21 -> 30.111 | G7: =Assumptions!G21 -> 62.01035 | H7: =Assumptions!H21 -> 106.9263 | I7: =Assumptions!I21 -> 161.4895 | K7: =D7/D6 -> 0.46563803 | L7: =E7/E6 -> 0.26242239 | M7: =F7/F6 -> 0.20805307 | N7: =G7/G6 -> 0.17648916 | O7: =H7/H6 -> 0.14616503 | P7: =I7/I6 -> 0.11635109 | R7: Segment-weighted: each revenue line carries its own gross margin (see Assumptions). Blended gross margin expands from 53% to 88% as the mix shifts toward high-margin silicon and software and as the 28nm mask amortises across volume.
B8: Gross Profit | D8: =D6-D7 -> 3.2035 | E8: =E6-E7 -> 30.36312 | F8: =F6-F7 -> 114.6165 | G8: =G6-G7 -> 289.34465 | H8: =H6-H7 -> 624.6187 | I8: =I6-I7 -> 1226.4605 | K8: =D8/D6 -> 0.53436197 | L8: =E8/E6 -> 0.73757761 | M8: =F8/F6 -> 0.79194693 | N8: =G8/G6 -> 0.82351084 | O8: =H8/H6 -> 0.85383497 | P8: =I8/I6 -> 0.88364891 | R8: Margin expansion is structural, not assumed — it follows the FPGA?ASIC cost transition (die cost falls ~16× at volume) and a rising software/licence attach rate.
B10: Overheads
B11: Payroll | D11: =Payroll!Y18 -> 2.1136501 | E11: =Payroll!Z18 -> 5.0889348 | F11: =Payroll!AA18 -> 8.9993915 | G11: =Payroll!AB18 -> 13.132072 | H11: =Payroll!AC18 -> 22.449561 | I11: =Payroll!AD18 -> 42.588139 | K11: =D11/D$6 -> 0.35256883 | L11: =E11/E$6 -> 0.12361985 | M11: =F11/F$6 -> 0.062181627 | N11: =G11/G$6 -> 0.03737551 | O11: =H11/H$6 -> 0.030687874 | P11: =I11/I$6 -> 0.030684202 | R11: Fully-loaded headcount cost, built bottom-up by department (see Payroll). Shown as a discrete line for transparency; the R&D, S&M and G&A lines below are non-payroll only, so there is no double-counting. Payroll falls from ~35% of revenue to ~3% as the team scales sub-linearly to revenue.
B12: R&D (total) | D12: =SUM(D13:D14) -> 1.7302551 | E12: =SUM(E13:E14) -> 12.916953 | F12: =SUM(F13:F14) -> 42.788685 | G12: =SUM(G13:G14) -> 104.52811 | H12: =SUM(H13:H14) -> 208.30744 | I12: =SUM(I13:I14) -> 377.86939 | K12: =D12/D$6 -> 0.28861637 | L12: =E12/E$6 -> 0.31377723 | M12: =F12/F$6 -> 0.29565 | N12: =G12/G$6 -> 0.2975 | O12: =H12/H$6 -> 0.28475 | P12: =I12/I$6 -> 0.27225 | R12: Two components: run-rate R&D sustaining the SoC2 platform and software, plus a dedicated SoC4 5nm program for the next-generation L4/robotaxi compute. Combined with R&D salaries above, total R&D investment runs ~30–35% of revenue — deliberately high, reflecting continuous silicon development as the core moat.
B13: run-rate R&D | D13: ='Expense Schedules'!D10 -> 1.3302551 | E13: ='Expense Schedules'!E10 -> 6.6339927 | F13: ='Expense Schedules'!F10 -> 23.445855 | G13: ='Expense Schedules'!G10 -> 49.1897 | H13: ='Expense Schedules'!H10 -> 87.053855 | I13: ='Expense Schedules'!I10 -> 137.40705 | K13: =D13/D$6 -> 0.2218941 | L13: =E13/E$6 -> 0.16115223 | M13: =F13/F$6 -> 0.162 | N13: =G13/G$6 -> 0.14 | O13: =H13/H$6 -> 0.119 | P13: =I13/I$6 -> 0.099
B14: SoC4 5nm tape-out program | D14: ='Expense Schedules'!D11 -> 0.4 | E14: ='Expense Schedules'!E11 -> 6.2829607 | F14: ='Expense Schedules'!F11 -> 19.34283 | G14: ='Expense Schedules'!G11 -> 55.338412 | H14: ='Expense Schedules'!H11 -> 121.25358 | I14: ='Expense Schedules'!I11 -> 240.46234 | K14: =D14/D$6 -> 0.066722269 | L14: =E14/E$6 -> 0.152625 | M14: =F14/F$6 -> 0.13365 | N14: =G14/G$6 -> 0.1575 | O14: =H14/H$6 -> 0.16575 | P14: =I14/I$6 -> 0.17325 | R14: Forward investment in the next-generation datacenter-class chip. Independent of the core ADAS business and discretionary — it can be deferred to accelerate profitability without affecting the primary revenue plan.
B15: Sales & Marketing | D15: ='Expense Schedules'!D34 -> 0.56 | E15: ='Expense Schedules'!E34 -> 5.85291 | F15: ='Expense Schedules'!F34 -> 20.070186 | G15: ='Expense Schedules'!G34 -> 47.081541 | H15: ='Expense Schedules'!H34 -> 94.424436 | I15: ='Expense Schedules'!I34 -> 172.21823 | K15: =D15/D$6 -> 0.093411176 | L15: =E15/E$6 -> 0.14217825 | M15: =F15/F$6 -> 0.13867569 | N15: =G15/G$6 -> 0.13399992 | O15: =H15/H$6 -> 0.12907536 | P15: =I15/I$6 -> 0.124081 | R15: Non-payroll go-to-market spend (demand generation, field pilots, channel, events). Runs ~13% of revenue at scale, consistent with a field-sales-led kit and fleet model serving commercial-vehicle and OEM channels.
B16: G&A | D16: ='Expense Schedules'!D24 -> 0.5995 | E16: ='Expense Schedules'!E24 -> 3.91077 | F16: ='Expense Schedules'!F24 -> 13.025475 | G16: ='Expense Schedules'!G24 -> 28.1084 | H16: ='Expense Schedules'!H24 -> 58.5236 | I16: ='Expense Schedules'!I24 -> 97.1565 | K16: =D16/D$6 -> 0.1 | L16: =E16/E$6 -> 0.095 | M16: =F16/F$6 -> 0.09 | N16: =G16/G$6 -> 0.08 | O16: =H16/H$6 -> 0.08 | P16: =I16/I$6 -> 0.07 | R16: Non-payroll general and administrative (facilities, legal and IP, audit, insurance, IT). Declines from 10% to 7% of revenue as fixed overhead is leveraged across a growing base.
B17: Total Overheads | D17: =D11+D12+D15+D16 -> 5.0034053 | E17: =E11+E12+E15+E16 -> 27.769568 | F17: =F11+F12+F15+F16 -> 84.883738 | G17: =G11+G12+G15+G16 -> 192.85013 | H17: =H11+H12+H15+H16 -> 383.70504 | I17: =I11+I12+I15+I16 -> 689.83225 | K17: =D17/D6 -> 0.83459638 | L17: =E17/E6 -> 0.67457533 | M17: =F17/F6 -> 0.58650732 | N17: =G17/G6 -> 0.54887543 | O17: =H17/H6 -> 0.52451324 | P17: =I17/I6 -> 0.4970152
B19: EBITDA | D19: =D8-D17 -> -1.7999053 | E19: =E8-E17 -> 2.5935518 | F19: =F8-F17 -> 29.732762 | G19: =G8-G17 -> 96.494524 | H19: =H8-H17 -> 240.91366 | I19: =I8-I17 -> 536.62825 | K19: =D19/D6 -> -0.30023441 | L19: =E19/E6 -> 0.063002278 | M19: =F19/F6 -> 0.20543962 | N19: =G19/G6 -> 0.27463541 | O19: =H19/H6 -> 0.32932173 | P19: =I19/I6 -> 0.3866337 | R19: Reaches the low-to-mid 30s% at scale — consistent with leading fabless-semiconductor economics. The one-time R&D, infinite-margin-at-scale model drives operating leverage as the 28nm die replaces FPGA hardware in the cost base
B21: D&A | D21: 0.1199 | E21: 0.82332 | F21: 2.89455 | G21: 7.0271 | H21: 14.6309 | I21: 27.759 | K21: =D21/D6 -> 0.02 | L21: =E21/E6 -> 0.02 | M21: =F21/F6 -> 0.02 | N21: =G21/G6 -> 0.02 | O21: =H21/H6 -> 0.02 | P21: =I21/I6 -> 0.02 | R21: Modest, reflecting the fabless model — no fabrication capex. Primarily amortisation of capitalised design/NRE cost rather than plant depreciation.
B22: EBIT | D22: =D19-D21 -> -1.9198053 | E22: =E19-E21 -> 1.7702318 | F22: =F19-F21 -> 26.838212 | G22: =G19-G21 -> 89.467424 | H22: =H19-H21 -> 226.28276 | I22: =I19-I21 -> 508.86925 | K22: =D22/D6 -> -0.32023441 | L22: =E22/E6 -> 0.043002278 | M22: =F22/F6 -> 0.18543962 | N22: =G22/G6 -> 0.25463541 | O22: =H22/H6 -> 0.30932173 | P22: =I22/I6 -> 0.3666337
B24: Interest | D24: ='CGTMSE Debt '!D9 -> 0.375 | E24: =D24 -> 0.375 | F24: =E24 -> 0.375 | G24: =F24 -> 0.375 | H24: =G24 -> 0.375 | I24: =H24 -> 0.375 | K24: =D24/D6 -> 0.062552127 | L24: =E24/E6 -> 0.0091094593 | M24: =F24/F6 -> 0.0025910763 | N24: =G24/G6 -> 0.0010672966 | O24: =H24/H6 -> 0.00051261371 | P24: =I24/I6 -> 0.00027018264 | R24: On the 10 Cr CGTMSE-backed working-capital facility (collateral-free MSME scheme) at an assumed 25% drawdown — non-dilutive capital that preserves equity for silicon.
B25: EBT | D25: =D22-D24 -> -2.2948053 | E25: =E22-E24 -> 1.3952318 | F25: =F22-F24 -> 26.463212 | G25: =G22-G24 -> 89.092424 | H25: =H22-H24 -> 225.90776 | I25: =I22-I24 -> 508.49425 | K25: =D25/D6 -> -0.38278654 | L25: =E25/E6 -> 0.033892819 | M25: =F25/F6 -> 0.18284854 | N25: =G25/G6 -> 0.25356811 | O25: =H25/H6 -> 0.30880912 | P25: =I25/I6 -> 0.36636352
B27: Loss Carryforward | D27: 0 | E27: =D25 -> -2.2948053 | F27: 0 | G27: 0 | H27: 0 | I27: 0
B28: Taxable Income | D28: =D25-D27 -> -2.2948053 | E28: =E25+E27 -> -0.89957351 | F28: =F25+F27 -> 26.463212 | G28: =G25+G27 -> 89.092424 | H28: =H25+H27 -> 225.90776 | I28: =I25+I27 -> 508.49425
B29: Tax (@25%) | D29: 0 | E29: =E28*0.25 -> -0.22489338 | F29: =F28*0.25 -> 6.615803 | G29: =G28*0.25 -> 22.273106 | H29: =H28*0.25 -> 56.476941 | I29: =I28*0.25 -> 127.12356 | K29: =D29/D28 -> 0 | L29: =E29/E28 -> 0.25 | M29: =F29/F28 -> 0.25 | N29: =G29/G28 -> 0.25 | O29: =H29/H28 -> 0.25 | P29: =I29/I28 -> 0.25 | R29: Standard 25% corporate rate, applied after utilising FY2027–FY2028 carried-forward losses.
B31: Net Income | D31: =D28-D29 -> -2.2948053 | E31: =E28-E29 -> -0.67468013 | F31: =F28-F29 -> 19.847409 | G31: =G28-G29 -> 66.819318 | H31: =H28-H29 -> 169.43082 | I31: =I28-I29 -> 381.37069 | K31: =D31/D6 -> -0.38278654 | L31: =E31/E6 -> -0.016389256 | M31: =F31/F6 -> 0.13713641 | N31: =G31/G6 -> 0.19017608 | O31: =H31/H6 -> 0.23160684 | P31: =I31/I6 -> 0.27477264 | R31: Company turns profitable at the net level in FY2029, the first full year of ASIC-based revenue — two years after the round

Sheet Sales Summary
B2: DeepGrid Semi Private Limited
B3: Projected Sales Summary
B5: Revenue by Business Line | D5: Revenue (In Cr.) | K5: Margins
B6: Platform | C6: x | D6: FY2027 | E6: FY2028 | F6: FY2029 | G6: FY2030 | H6: FY2031 | I6: FY2032 | J6: x | K6: FY2027 | L6: FY2028 | M6: FY2029 | N6: FY2030 | O6: FY2031 | P6: FY2032
B7: Silicon | D7: =SUMIF('Revenue Master'!$D:$D,'Sales Summary'!$B7,'Revenue Master'!I:I) -> 0 | E7: =SUMIF('Revenue Master'!$D:$D,'Sales Summary'!$B7,'Revenue Master'!J:J) -> 0.354 | F7: =SUMIF('Revenue Master'!$D:$D,'Sales Summary'!$B7,'Revenue Master'!K:K) -> 3.75 | G7: =SUMIF('Revenue Master'!$D:$D,'Sales Summary'!$B7,'Revenue Master'!L:L) -> 12 | H7: =SUMIF('Revenue Master'!$D:$D,'Sales Summary'!$B7,'Revenue Master'!M:M) -> 33 | I7: =SUMIF('Revenue Master'!$D:$D,'Sales Summary'!$B7,'Revenue Master'!N:N) -> 75 | K7: =D7/D$12 -> 0 | L7: =E7/E$12 -> 0.0085993295 | M7: =F7/F$12 -> 0.025910763 | N7: =G7/G$12 -> 0.034153491 | O7: =H7/H$12 -> 0.045110007 | P7: =I7/I$12 -> 0.054036529
B8: Sensors | D8: =SUMIF('Revenue Master'!$D:$D,'Sales Summary'!$B8,'Revenue Master'!I:I) -> 0.375 | E8: =SUMIF('Revenue Master'!$D:$D,'Sales Summary'!$B8,'Revenue Master'!J:J) -> 1.45 | F8: =SUMIF('Revenue Master'!$D:$D,'Sales Summary'!$B8,'Revenue Master'!K:K) -> 3.975 | G8: =SUMIF('Revenue Master'!$D:$D,'Sales Summary'!$B8,'Revenue Master'!L:L) -> 9 | H8: =SUMIF('Revenue Master'!$D:$D,'Sales Summary'!$B8,'Revenue Master'!M:M) -> 18.5 | I8: =SUMIF('Revenue Master'!$D:$D,'Sales Summary'!$B8,'Revenue Master'!N:N) -> 33.5 | K8: =D8/D$12 -> 0.062552127 | L8: =E8/E$12 -> 0.035223242 | M8: =F8/F$12 -> 0.027465409 | N8: =G8/G$12 -> 0.025615119 | O8: =H8/H$12 -> 0.025288943 | P8: =I8/I$12 -> 0.024136316
B9: Systems | D9: =SUMIF('Revenue Master'!$D:$D,'Sales Summary'!$B9,'Revenue Master'!I:I) -> 5.62 | E9: =SUMIF('Revenue Master'!$D:$D,'Sales Summary'!$B9,'Revenue Master'!J:J) -> 39.362 | F9: =SUMIF('Revenue Master'!$D:$D,'Sales Summary'!$B9,'Revenue Master'!K:K) -> 135.0025 | G9: =SUMIF('Revenue Master'!$D:$D,'Sales Summary'!$B9,'Revenue Master'!L:L) -> 324.355 | H9: =SUMIF('Revenue Master'!$D:$D,'Sales Summary'!$B9,'Revenue Master'!M:M) -> 662.045 | I9: =SUMIF('Revenue Master'!$D:$D,'Sales Summary'!$B9,'Revenue Master'!N:N) -> 1229.45 | K9: =D9/D$12 -> 0.93744787 | L9: =E9/E$12 -> 0.95617743 | M9: =F9/F$12 -> 0.93280475 | N9: =G9/G$12 -> 0.92315464 | O9: =H9/H$12 -> 0.90499559 | P9: =I9/I$12 -> 0.8858028
B10: Sentience | D10: =SUMIF('Revenue Master'!$D:$D,'Sales Summary'!$B10,'Revenue Master'!I:I) -> 0 | E10: =SUMIF('Revenue Master'!$D:$D,'Sales Summary'!$B10,'Revenue Master'!J:J) -> 0 | F10: =SUMIF('Revenue Master'!$D:$D,'Sales Summary'!$B10,'Revenue Master'!K:K) -> 2 | G10: =SUMIF('Revenue Master'!$D:$D,'Sales Summary'!$B10,'Revenue Master'!L:L) -> 6 | H10: =SUMIF('Revenue Master'!$D:$D,'Sales Summary'!$B10,'Revenue Master'!M:M) -> 18 | I10: =SUMIF('Revenue Master'!$D:$D,'Sales Summary'!$B10,'Revenue Master'!N:N) -> 50 | K10: =D10/D$12 -> 0 | L10: =E10/E$12 -> 0 | M10: =F10/F$12 -> 0.013819074 | N10: =G10/G$12 -> 0.017076746 | O10: =H10/H$12 -> 0.024605458 | P10: =I10/I$12 -> 0.036024352
B12: Total | D12: =SUBTOTAL(9,D7:D10) -> 5.995 | E12: =SUBTOTAL(9,E7:E10) -> 41.166 | F12: =SUBTOTAL(9,F7:F10) -> 144.7275 | G12: =SUBTOTAL(9,G7:G10) -> 351.355 | H12: =SUBTOTAL(9,H7:H10) -> 731.545 | I12: =SUBTOTAL(9,I7:I10) -> 1387.95 | K12: =D12/D$12 -> 1 | L12: =E12/E$12 -> 1 | M12: =F12/F$12 -> 1 | N12: =G12/G$12 -> 1 | O12: =H12/H$12 -> 1 | P12: =I12/I$12 -> 1
B14: Revenue by Product Category | D14: Revenue (In Cr.) | K14: Margins
B15: Platform | C15: x | D15: FY2027 | E15: FY2028 | F15: FY2029 | G15: FY2030 | H15: FY2031 | I15: FY2032 | K15: FY2027 | L15: FY2028 | M15: FY2029 | N15: FY2030 | O15: FY2031 | P15: FY2032
B16: Chipsets | D16: =SUMIF('Revenue Master'!$E:$E,'Sales Summary'!$B16,'Revenue Master'!I:I) -> 0 | E16: =SUMIF('Revenue Master'!$E:$E,'Sales Summary'!$B16,'Revenue Master'!J:J) -> 0.354 | F16: =SUMIF('Revenue Master'!$E:$E,'Sales Summary'!$B16,'Revenue Master'!K:K) -> 3.75 | G16: =SUMIF('Revenue Master'!$E:$E,'Sales Summary'!$B16,'Revenue Master'!L:L) -> 12 | H16: =SUMIF('Revenue Master'!$E:$E,'Sales Summary'!$B16,'Revenue Master'!M:M) -> 33 | I16: =SUMIF('Revenue Master'!$E:$E,'Sales Summary'!$B16,'Revenue Master'!N:N) -> 75 | K16: =D16/D$12 -> 0 | L16: =E16/E$12 -> 0.0085993295 | M16: =F16/F$12 -> 0.025910763 | N16: =G16/G$12 -> 0.034153491 | O16: =H16/H$12 -> 0.045110007 | P16: =I16/I$12 -> 0.054036529
B17: Sensor Modules | D17: =SUMIF('Revenue Master'!$E:$E,'Sales Summary'!$B17,'Revenue Master'!I:I) -> 0.375 | E17: =SUMIF('Revenue Master'!$E:$E,'Sales Summary'!$B17,'Revenue Master'!J:J) -> 1.45 | F17: =SUMIF('Revenue Master'!$E:$E,'Sales Summary'!$B17,'Revenue Master'!K:K) -> 3.975 | G17: =SUMIF('Revenue Master'!$E:$E,'Sales Summary'!$B17,'Revenue Master'!L:L) -> 9 | H17: =SUMIF('Revenue Master'!$E:$E,'Sales Summary'!$B17,'Revenue Master'!M:M) -> 18.5 | I17: =SUMIF('Revenue Master'!$E:$E,'Sales Summary'!$B17,'Revenue Master'!N:N) -> 33.5 | K17: =D17/D$12 -> 0.062552127 | L17: =E17/E$12 -> 0.035223242 | M17: =F17/F$12 -> 0.027465409 | N17: =G17/G$12 -> 0.025615119 | O17: =H17/H$12 -> 0.025288943 | P17: =I17/I$12 -> 0.024136316
B18: Robotics Systems | D18: =SUMIF('Revenue Master'!$E:$E,'Sales Summary'!$B18,'Revenue Master'!I:I) -> 2.12 | E18: =SUMIF('Revenue Master'!$E:$E,'Sales Summary'!$B18,'Revenue Master'!J:J) -> 6.4 | F18: =SUMIF('Revenue Master'!$E:$E,'Sales Summary'!$B18,'Revenue Master'!K:K) -> 20.1 | G18: =SUMIF('Revenue Master'!$E:$E,'Sales Summary'!$B18,'Revenue Master'!L:L) -> 44 | H18: =SUMIF('Revenue Master'!$E:$E,'Sales Summary'!$B18,'Revenue Master'!M:M) -> 89.6 | I18: =SUMIF('Revenue Master'!$E:$E,'Sales Summary'!$B18,'Revenue Master'!N:N) -> 153 | K18: =D18/D$12 -> 0.35362802 | L18: =E18/E$12 -> 0.1554681 | M18: =F18/F$12 -> 0.13888169 | N18: =G18/G$12 -> 0.12522947 | O18: =H18/H$12 -> 0.1224805 | P18: =I18/I$12 -> 0.11023452
B19: Mobility Systems | D19: =SUMIF('Revenue Master'!$E:$E,'Sales Summary'!$B19,'Revenue Master'!I:I) -> 3.5 | E19: =SUMIF('Revenue Master'!$E:$E,'Sales Summary'!$B19,'Revenue Master'!J:J) -> 27.056 | F19: =SUMIF('Revenue Master'!$E:$E,'Sales Summary'!$B19,'Revenue Master'!K:K) -> 101.115 | G19: =SUMIF('Revenue Master'!$E:$E,'Sales Summary'!$B19,'Revenue Master'!L:L) -> 251.53 | H19: =SUMIF('Revenue Master'!$E:$E,'Sales Summary'!$B19,'Revenue Master'!M:M) -> 516.045 | I19: =SUMIF('Revenue Master'!$E:$E,'Sales Summary'!$B19,'Revenue Master'!N:N) -> 966.15 | K19: =D19/D$12 -> 0.58381985 | L19: =E19/E$12 -> 0.65724141 | M19: =F19/F$12 -> 0.69865782 | N19: =G19/G$12 -> 0.71588564 | O19: =H19/H$12 -> 0.70541799 | P19: =I19/I$12 -> 0.69609856
B20: Compute Hardware | D20: =SUMIF('Revenue Master'!$E:$E,'Sales Summary'!$B20,'Revenue Master'!I:I) -> 0 | E20: =SUMIF('Revenue Master'!$E:$E,'Sales Summary'!$B20,'Revenue Master'!J:J) -> 5.906 | F20: =SUMIF('Revenue Master'!$E:$E,'Sales Summary'!$B20,'Revenue Master'!K:K) -> 13.7875 | G20: =SUMIF('Revenue Master'!$E:$E,'Sales Summary'!$B20,'Revenue Master'!L:L) -> 28.825 | H20: =SUMIF('Revenue Master'!$E:$E,'Sales Summary'!$B20,'Revenue Master'!M:M) -> 56.4 | I20: =SUMIF('Revenue Master'!$E:$E,'Sales Summary'!$B20,'Revenue Master'!N:N) -> 110.3 | K20: =D20/D$12 -> 0 | L20: =E20/E$12 -> 0.14346791 | M20: =F20/F$12 -> 0.09526524 | N20: =G20/G$12 -> 0.082039533 | O20: =H20/H$12 -> 0.077097103 | P20: =I20/I$12 -> 0.079469722
B21: AI Software / SaaS | D21: =SUMIF('Revenue Master'!$E:$E,'Sales Summary'!$B21,'Revenue Master'!I:I) -> 0 | E21: =SUMIF('Revenue Master'!$E:$E,'Sales Summary'!$B21,'Revenue Master'!J:J) -> 0 | F21: =SUMIF('Revenue Master'!$E:$E,'Sales Summary'!$B21,'Revenue Master'!K:K) -> 2 | G21: =SUMIF('Revenue Master'!$E:$E,'Sales Summary'!$B21,'Revenue Master'!L:L) -> 6 | H21: =SUMIF('Revenue Master'!$E:$E,'Sales Summary'!$B21,'Revenue Master'!M:M) -> 18 | I21: =SUMIF('Revenue Master'!$E:$E,'Sales Summary'!$B21,'Revenue Master'!N:N) -> 50 | K21: =D21/D$12 -> 0 | L21: =E21/E$12 -> 0 | M21: =F21/F$12 -> 0.013819074 | N21: =G21/G$12 -> 0.017076746 | O21: =H21/H$12 -> 0.024605458 | P21: =I21/I$12 -> 0.036024352
B23: Total | D23: =SUBTOTAL(9,D16:D21) -> 5.995 | E23: =SUBTOTAL(9,E16:E21) -> 41.166 | F23: =SUBTOTAL(9,F16:F21) -> 144.7275 | G23: =SUBTOTAL(9,G16:G21) -> 351.355 | H23: =SUBTOTAL(9,H16:H21) -> 731.545 | I23: =SUBTOTAL(9,I16:I21) -> 1387.95 | K23: =D23/D$12 -> 1 | L23: =E23/E$12 -> 1 | M23: =F23/F$12 -> 1 | N23: =G23/G$12 -> 1 | O23: =H23/H$12 -> 1 | P23: =I23/I$12 -> 1
B26: Revenue by Commercial Model | D26: Revenue (In Cr.) | K26: Margins
B27: Platform | C27: x | D27: FY2027 | E27: FY2028 | F27: FY2029 | G27: FY2030 | H27: FY2031 | I27: FY2032 | K27: FY2027 | L27: FY2028 | M27: FY2029 | N27: FY2030 | O27: FY2031 | P27: FY2032
B28: Licence / OEM Supply | D28: =SUMIF('Revenue Master'!$F:$F,'Sales Summary'!$B28,'Revenue Master'!I:I) -> 0 | E28: =SUMIF('Revenue Master'!$F:$F,'Sales Summary'!$B28,'Revenue Master'!J:J) -> 0.354 | F28: =SUMIF('Revenue Master'!$F:$F,'Sales Summary'!$B28,'Revenue Master'!K:K) -> 3.75 | G28: =SUMIF('Revenue Master'!$F:$F,'Sales Summary'!$B28,'Revenue Master'!L:L) -> 12 | H28: =SUMIF('Revenue Master'!$F:$F,'Sales Summary'!$B28,'Revenue Master'!M:M) -> 33 | I28: =SUMIF('Revenue Master'!$F:$F,'Sales Summary'!$B28,'Revenue Master'!N:N) -> 75 | K28: =D28/D$12 -> 0 | L28: =E28/E$12 -> 0.0085993295 | M28: =F28/F$12 -> 0.025910763 | N28: =G28/G$12 -> 0.034153491 | O28: =H28/H$12 -> 0.045110007 | P28: =I28/I$12 -> 0.054036529
B29: Product Sales | D29: =SUMIF('Revenue Master'!$F:$F,'Sales Summary'!$B29,'Revenue Master'!I:I) -> 5.995 | E29: =SUMIF('Revenue Master'!$F:$F,'Sales Summary'!$B29,'Revenue Master'!J:J) -> 37.512 | F29: =SUMIF('Revenue Master'!$F:$F,'Sales Summary'!$B29,'Revenue Master'!K:K) -> 132.3775 | G29: =SUMIF('Revenue Master'!$F:$F,'Sales Summary'!$B29,'Revenue Master'!L:L) -> 316.855 | H29: =SUMIF('Revenue Master'!$F:$F,'Sales Summary'!$B29,'Revenue Master'!M:M) -> 647.545 | I29: =SUMIF('Revenue Master'!$F:$F,'Sales Summary'!$B29,'Revenue Master'!N:N) -> 1196.95 | K29: =D29/D$12 -> 1 | L29: =E29/E$12 -> 0.91123743 | M29: =F29/F$12 -> 0.91466722 | N29: =G29/G$12 -> 0.90180871 | O29: =H29/H$12 -> 0.88517453 | P29: =I29/I$12 -> 0.86238697
B30: Rental / TaaS | D30: =SUMIF('Revenue Master'!$F:$F,'Sales Summary'!$B30,'Revenue Master'!I:I) -> 0 | E30: =SUMIF('Revenue Master'!$F:$F,'Sales Summary'!$B30,'Revenue Master'!J:J) -> 3.3 | F30: =SUMIF('Revenue Master'!$F:$F,'Sales Summary'!$B30,'Revenue Master'!K:K) -> 6.6 | G30: =SUMIF('Revenue Master'!$F:$F,'Sales Summary'!$B30,'Revenue Master'!L:L) -> 16.5 | H30: =SUMIF('Revenue Master'!$F:$F,'Sales Summary'!$B30,'Revenue Master'!M:M) -> 33 | I30: =SUMIF('Revenue Master'!$F:$F,'Sales Summary'!$B30,'Revenue Master'!N:N) -> 66 | K30: =D30/D$12 -> 0 | L30: =E30/E$12 -> 0.080163242 | M30: =F30/F$12 -> 0.045602943 | N30: =G30/G$12 -> 0.046961051 | O30: =H30/H$12 -> 0.045110007 | P30: =I30/I$12 -> 0.047552145
B31: SaaS Subscription | D31: =SUMIF('Revenue Master'!$F:$F,'Sales Summary'!$B31,'Revenue Master'!I:I) -> 0 | E31: =SUMIF('Revenue Master'!$F:$F,'Sales Summary'!$B31,'Revenue Master'!J:J) -> 0 | F31: =SUMIF('Revenue Master'!$F:$F,'Sales Summary'!$B31,'Revenue Master'!K:K) -> 2 | G31: =SUMIF('Revenue Master'!$F:$F,'Sales Summary'!$B31,'Revenue Master'!L:L) -> 6 | H31: =SUMIF('Revenue Master'!$F:$F,'Sales Summary'!$B31,'Revenue Master'!M:M) -> 18 | I31: =SUMIF('Revenue Master'!$F:$F,'Sales Summary'!$B31,'Revenue Master'!N:N) -> 50 | K31: =D31/D$12 -> 0 | L31: =E31/E$12 -> 0 | M31: =F31/F$12 -> 0.013819074 | N31: =G31/G$12 -> 0.017076746 | O31: =H31/H$12 -> 0.024605458 | P31: =I31/I$12 -> 0.036024352
B33: Total | D33: =SUBTOTAL(9,D28:D31) -> 5.995 | E33: =SUBTOTAL(9,E28:E31) -> 41.166 | F33: =SUBTOTAL(9,F28:F31) -> 144.7275 | G33: =SUBTOTAL(9,G28:G31) -> 351.355 | H33: =SUBTOTAL(9,H28:H31) -> 731.545 | I33: =SUBTOTAL(9,I28:I31) -> 1387.95 | K33: =D33/D$12 -> 1 | L33: =E33/E$12 -> 1 | M33: =F33/F$12 -> 1 | N33: =G33/G$12 -> 1 | O33: =H33/H$12 -> 1 | P33: =I33/I$12 -> 1

Sheet Use of Funds
B2: DeepGrid Semi Private Limited
B3: Use of Funds
B5: Sources of Capital | D5: Revenue
B6: Sources | C6: x | D6: $ M | E6: Rs. Cr | H6: Comments
B7: Pre-Series A equity round | D7: 4.787234 | E7: =D7*Assumptions!$D$5/10 -> 45 | H7: Equity; funds the SoC2 tapeout (18.07% to investor)
B8: CGTMSE-backed term loan | D8: 1.0638298 | E8: =D8*Assumptions!$D$5/10 -> 10 | H8: Rs10 Cr (~$1.06M) collateral-free MSME debt; funds working capital, non-dilutive
B10: Total | D10: =SUM(D7:D8) -> 5.8510638 | E10: =SUBTOTAL(9,E7:E8) -> 55 | H10: 55 Cr blended: 45 Cr equity funds the value-creating silicon and tapeout; 10 Cr non-dilutive CGTMSE debt funds working capital. Dilution is tied only to the milestone that creates enterprise value.
B12: Use of Capital | D12: Revenue
B13: Allocation | C13: x | D13: $ M | E13: Rs. Cr | F13: % OF Total | H13: Comment
B14: SoC2 tapeout NRE + IP (phased: MPW blocks -> full die -> dedicated mask) | D14: 3.17 | E14: =D14*Assumptions!$D$5/10 -> 29.798 | F14: =E14/$E$19 -> 0.54188034 | H14: Equity-funded; see Tapeout tab
B15: Engineering (chip + firmware + defence) | D15: 0.96 | E15: =D15*Assumptions!$D$5/10 -> 9.024 | F15: =E15/$E$19 -> 0.16410256 | H15: Core platform R&D
B16: AIS-162/188 certification + FPGA pilot | D16: 0.48 | E16: =D16*Assumptions!$D$5/10 -> 4.512 | F16: =E16/$E$19 -> 0.082051282 | H16: Mandate compliance + pilots
B17: Working capital / BD / inventory | D17: 1.24 | E17: =D17*Assumptions!$D$5/10 -> 11.656 | F17: =E17/$E$19 -> 0.21196581 | H17: L4+ stack, field units
B19: Total | D19: =SUBTOTAL(9,D14:D17) -> 5.85 | E19: =SUBTOTAL(9,E14:E17) -> 54.99 | F19: =E19/E19 -> 1 | H19: Equity round is ~all silicon; loan covers working capital

Sheet Historical Context
B2: DeepGrid Semi Private Limited
B3: Grants & Prior Funding
B5: Particulars | C5: x | D5: Amount (In Cr.) | E5: x | F5: Comments
B6: ARAI certification grant | D6: 0.36 | F6: Rs. 36 lakh - received
B7: HDFC Parivartan grant | D7: 0.12 | F7: Rs. 12 Lakh - received - used for FPGA
B8: Angel funding to date | D8: 2 | F8: ~Rs. 2 Cr — fully deployed in operations (bank statement verified)

Sheet CGTMSE Debt 
B2: DeepGrid Semi Private Limited
B3: CGTMSE Debt Amortisation Schedule
B5: Particulars | C5: x | D5: Amount (In Cr.)
B6: Overdraft Limit | D6: 10
B7: Interest Rate | D7: 0.15
B8: Assumed Utilization Rate | D8: 0.25
B9: Finance Cost | D9: =D6*D8*D7 -> 0.375

Sheet Cap Table
B2: DeepGrid Semi Private Limited
B3: Cap Table
B5: Name of the Shareholder | C5: Type of Shareholders | D5: No of Shares | E5: % of Shareholding | F5: x | G5: Comments
B6: Muralidhar Naidu Govardhan | C6: Founder's Shares | D6: 1000 | E6: =D6/$D$13 -> 0.0097279103 | G6: Founder-led, with early angels who are domain operators (including DFT/semiconductor engineers backing the company personally) — conviction capital from people who understand silicon.
B7: Aravind Prasad Govardhan | C7: Founder's Shares | D7: 98300 | E7: =D7/$D$13 -> 0.95625359
B8: Venkata | C8: Angels | D8: 697 | E8: =D8/$D$13 -> 0.0067803535
B9: Navin | C9: Angels | D9: 121 | E9: =D9/$D$13 -> 0.0011770772
B10: Hameed | C10: Angels | D10: 893 | E10: =D10/$D$13 -> 0.0086870239
B11: Raghu Teja | C11: Angels | D11: 893 | E11: =D11/$D$13 -> 0.0086870239
B12: Tejovardhan | C12: Angels | D12: 893 | E12: =D12/$D$13 -> 0.0086870239
B13: Total Shares | D13: =SUM(D6:D12) -> 102797 | E13: =SUM(E6:E12) -> 1

Sheet Market
B2: DeepGrid Semi Private Limited
B3: Market Analysis
B5: MARKET FUNNEL (TAM -> SAM -> SOM)
B6: Layer | C6: x | D6: Value | E6: Unit | H6: Source and Comment
B7: India commercial-vehicle market (2025) | D7: 53.2 | E7: $B | H7: IMARC 2025: $53.2B; Mordor $51.1B (corroborating)
B8: India ADAS market (2024) | D8: 2.29 | E8: $B | H8: EMR 2024: $2.29B, 20.6% CAGR to ~$14.9B by 2034
B9: TAM — mandated ADAS (AIS-184/186/187/188) annual | D9: 200 | E9: $M | H9: Telematicswire/Roadzen on GSR 184(E)
B10: SAM — N2/N3 trucks we target (new + retrofit) | D10: 1 | E10: M units | H10: ~500k new/yr + ~500k retrofit (Roadzen/MoRTH)
B11: Annual new N2/N3 + bus production (mandated from FY26) | D11: 0.5 | E11: M units/yr | H11: GSR 184(E) new-model scope, Apr 1 2026
B12: Retrofit pool (existing N2/N3 fleet) | D12: 0.5 | E12: M units | H12: GSR 184(E) existing-model scope, Oct 1 2026
B14: SOM — Our Reachable Share
B15: Platform | C15: x | D15: Particulars | H15: Source and Comment
B16: AD2 (mandatory) units at FY32 (from our build) | D16: 18000 | H16: AD2 satisfies the AIS-184 ADAS mandate on N2/N3 trucks
B17: AD2 share of 1.0M mandated trucks (new+retrofit) | D17: 0.018 | H17: Single-digit share of the mandated pool; mandate = demand floor
B18: AD0 (360 surround-view) units at FY32 | D18: 54000 | H18: NOT mandated — voluntary safety/convenience buy, already selling
B19: AD0 addressable: 360 surround-view market (2025) | D19: $3.09B | H19: Towards Automotive: $3.09B 2025, 10.7% CAGR; Maruti/Tata already fitting
B21: PER-PRODUCT DEMAND (every line tied to a sourced market pool)
B22: Product | C22: x | D22: FY2032 Units | E22: Demand Pool and Market Size | F22: Capture % | H22: Source and Comment
B23: Smart Truck (AD2 kit) | D23: 18000 | E23: MANDATORY: 0.5M new N2/N3 trucks/yr + 0.5M retrofit | F23: 0.018 | H23: MoRTH GSR 184(E) ADAS mandate on N2/N3
B24: AD0 Smart Mirror (mandate retrofit) | D24: 54000 | E24: Existing 360 surround-view market $3.1B (already selling) | F24: 0.0092956001 | H24: Towards Automotive: $3.09B 2025, 10.7% CAGR
B25: AD1 Indoor L4 kit | D25: 4200 | E25: Warehouse/industrial autonomy; part of $4.8B edge-AI | F25: — | H25: Dataintelo/GMI automotive edge-AI 2025
B26: Autonomous TaaS (fleet) | D26: 100 | E26: India trucking 0.6-0.8M units/yr; fleet ops | F26: 0.00014285714 | H26: Mobility Foresights; TheGlobalEconomy 952k CV
B27: Seaport AGV (port autonomy) | D27: 50 | E27: Automated container terminal market $10.95B (2024) | F27: 0.00022005246 | H27: SNS Insider: $10.95B 2024 -> $16.35B 2032, 5.2% CAGR
B28: A100 compute box (3 SKUs) | D28: 6000 | E28: Automotive edge-AI accelerator modules $4.8B (2025) | F28: 0.0020013298 | H28: Dataintelo: $4.8B 2025 -> $22.6B 2034, 21% CAGR
B29: Chipset OEM B2B (ASIC die) | D29: 30000 | E29: India ADAS chip pool; $2.29B ADAS (2024) | F29: 0.0025085943 | H29: EMR 2024: $2.29B, 20.6% CAGR
B30: Thermal camera (aftermarket) | D30: 3200 | E30: Automotive thermal camera $1.68B global (2025) | F30: 0.0010131712 | H30: Verified Market Research: $1.68B 2025, 12% CAGR
B31: 4D radar pod (aftermarket) | D31: 3000 | E31: 4D imaging radar $2.75B global (2025) | F31: 0.0002901354 | H31: Business Research Co./Mordor: ~$2.75B 2025, 13% CAGR
B32: H100 driver-monitor wearable | D32: 20000 | E32: DDAWS mandate (AIS-184) + global DMS demand | F32: — | H32: MoRTH AIS-184; EU Reg 2021/267 (commercial DMS)
B33: Defence D-HUMR | D33: 150 | E33: Indian Army UGV/robotics procurement | F33: — | H33: MoD/Army programs (existing Rs1 Cr revenue)
B34: D100 drone SoC kit | D34: 400 | E34: India defence + commercial drone SoC | F34: — | H34: Edge-AI drones segment (Mordor 18% CAGR)
B36: Every line maps to a real, sized market: the FY32 volumes are a single-digit share of each pool. Demand headroom is large, not stretched.
B38: Reading the Capture %:
B39: 1. Market sizes above are GLOBAL. Our near-term serviceable market is the India slice, where our share is materially higher — the small % = runway, not a ceiling.
B40: 2. Seaport AGV pool ($10.95B) is TOTAL port automation (cranes + software + vehicles); the autonomous-vehicle layer we sell is a subset. Real proof point: live order at Vizag Container Terminal.
B41: 3. Mandate timing: DDAWS / blind-spot / LDWS suite is live Apr & Oct 2026 (what AD2 demand rests on). The AEBS braking piece (AIS-162/IS-11852) was deferred to Oct 1 2027 (Gadkari, Lok Sabha, Feb 2026) — does not affect the 2026 ADAS suite.
B43: Sources: MoRTH GSR 184(E) 20 Mar 2025; Roadzen/Telematicswire; IMARC & Mordor (CV); EMR (ADAS); Dataintelo/GMI (edge-AI); Verified MR (thermal); Business Research Co. (4D radar); SNS Insider (container terminals). Share/conversion rows are our assumptions.

Sheet Working>>

Sheet Assumptions
B2: DeepGrid Semi Private Limited
B3: Modelling Assumptions
B5: USD / INR | C5: x | D5: 94
B7: Gross Margin by Business Line
B8: Segment | C8: x | D8: FY2027 | E8: FY2028 | F8: FY2029 | G8: FY2030 | H8: FY2031 | I8: FY2032 | J8: x | K8: Comment
B9: Silicon | D9: 0.55 | E9: 0.78 | F9: 0.86 | G9: 0.9 | H9: 0.92 | I9: 0.94 | K9: Fabless die margin: low at launch (low volume, NRE amortization, first-run yield), rising to ~94% at volume as wafer-cost/die falls and the mask is amortized.
B10: Sensors | D10: 0.3 | E10: 0.39 | F10: 0.42 | G10: 0.45 | H10: 0.48 | I10: 0.5 | K10: Hardware modules (4D radar, thermal, DMS) carry BOM + assembly; margin lower, rising modestly with scale and supplier negotiation.
B11: Systems | D11: 0.55 | E11: 0.75 | F11: 0.8 | G11: 0.83 | H11: 0.86 | I11: 0.89 | K11: Autonomy kits + compute boxes: blended HW+SW; SW/licence attach lifts margin sharply after the FY2027 pilot phase.
B12: Sentience | D12: 0.8 | E12: 0.84 | F12: 0.86 | G12: 0.88 | H12: 0.89 | I12: 0.9 | K12: Pure SaaS / AI licence — software economics, ~80–90% gross margin throughout.
B14: COGS Calculation
B15: Segment | C15: x | D15: FY2027 | E15: FY2028 | F15: FY2029 | G15: FY2030 | H15: FY2031 | I15: FY2032
B16: Silicon | D16: ='Sales Summary'!D7*(1-Assumptions!D9) -> 0 | E16: ='Sales Summary'!E7*(1-Assumptions!E9) -> 0.07788 | F16: ='Sales Summary'!F7*(1-Assumptions!F9) -> 0.525 | G16: ='Sales Summary'!G7*(1-Assumptions!G9) -> 1.2 | H16: ='Sales Summary'!H7*(1-Assumptions!H9) -> 2.64 | I16: ='Sales Summary'!I7*(1-Assumptions!I9) -> 4.5
B17: Sensors | D17: ='Sales Summary'!D8*(1-Assumptions!D10) -> 0.2625 | E17: ='Sales Summary'!E8*(1-Assumptions!E10) -> 0.8845 | F17: ='Sales Summary'!F8*(1-Assumptions!F10) -> 2.3055 | G17: ='Sales Summary'!G8*(1-Assumptions!G10) -> 4.95 | H17: ='Sales Summary'!H8*(1-Assumptions!H10) -> 9.62 | I17: ='Sales Summary'!I8*(1-Assumptions!I10) -> 16.75
B18: Systems | D18: ='Sales Summary'!D9*(1-Assumptions!D11) -> 2.529 | E18: ='Sales Summary'!E9*(1-Assumptions!E11) -> 9.8405 | F18: ='Sales Summary'!F9*(1-Assumptions!F11) -> 27.0005 | G18: ='Sales Summary'!G9*(1-Assumptions!G11) -> 55.14035 | H18: ='Sales Summary'!H9*(1-Assumptions!H11) -> 92.6863 | I18: ='Sales Summary'!I9*(1-Assumptions!I11) -> 135.2395
B19: Sentience | D19: ='Sales Summary'!D10*(1-Assumptions!D12) -> 0 | E19: ='Sales Summary'!E10*(1-Assumptions!E12) -> 0 | F19: ='Sales Summary'!F10*(1-Assumptions!F12) -> 0.28 | G19: ='Sales Summary'!G10*(1-Assumptions!G12) -> 0.72 | H19: ='Sales Summary'!H10*(1-Assumptions!H12) -> 1.98 | I19: ='Sales Summary'!I10*(1-Assumptions!I12) -> 5
B21: Total | D21: =SUM(D16:D19) -> 2.7915 | E21: =SUM(E16:E19) -> 10.80288 | F21: =SUM(F16:F19) -> 30.111 | G21: =SUM(G16:G19) -> 62.01035 | H21: =SUM(H16:H19) -> 106.9263 | I21: =SUM(I16:I19) -> 161.4895
B23: Expenses as a % of Revenue
B24: Overheads | C24: x | D24: FY2027 | E24: FY2028 | F24: FY2029 | G24: FY2030 | H24: FY2031 | I24: FY2032 | K24: Comment
B25: R&D % of revenue (total) | D25: ='P&L'!K12 -> 0.28861637 | E25: ='P&L'!L12 -> 0.31377723 | F25: ='P&L'!M12 -> 0.29565 | G25: ='P&L'!N12 -> 0.2975 | H25: ='P&L'!O12 -> 0.28475 | I25: ='P&L'!P12 -> 0.27225 | K25: Total R&D; split into run-rate + SoC4 5nm in P&L
B26: of which: run-rate R&D % | D26: ='P&L'!K13 -> 0.2218941 | E26: ='P&L'!L13 -> 0.16115223 | F26: ='P&L'!M13 -> 0.162 | G26: ='P&L'!N13 -> 0.14 | H26: ='P&L'!O13 -> 0.119 | I26: ='P&L'!P13 -> 0.099 | K26: Sustaining SoC2 + software; remainder funds SoC4 5nm
B27: Sales & Marketing % of revenue | D27: ='P&L'!K15 -> 0.093411176 | E27: ='P&L'!L15 -> 0.14217825 | F27: ='P&L'!M15 -> 0.13867569 | G27: ='P&L'!N15 -> 0.13399992 | H27: ='P&L'!O15 -> 0.12907536 | I27: ='P&L'!P15 -> 0.124081
B28: G&A % of revenue | D28: ='P&L'!K16 -> 0.1 | E28: ='P&L'!L16 -> 0.095 | F28: ='P&L'!M16 -> 0.09 | G28: ='P&L'!N16 -> 0.08 | H28: ='P&L'!O16 -> 0.08 | I28: ='P&L'!P16 -> 0.07
B29: D&A % of revenue | D29: ='P&L'!K21 -> 0.02 | E29: ='P&L'!L21 -> 0.02 | F29: ='P&L'!M21 -> 0.02 | G29: ='P&L'!N21 -> 0.02 | H29: ='P&L'!O21 -> 0.02 | I29: ='P&L'!P21 -> 0.02

Sheet Revenue Master
B2: DeepGrid Semi Private Limited
B3: Revenue Master
I4: Revenue(In Cr.) | P4: Volume | W4: ASP
B5: Product | C5: Chiplet | D5: Business Line | E5: Product Category | F5: Commercial Model | G5: Launch | H5: x | I5: FY2027 | J5: FY2028 | K5: FY2029 | L5: FY2030 | M5: FY2031 | N5: FY2032 | O5: x | P5: FY2027 | Q5: FY2028 | R5: FY2029 | S5: FY2030 | T5: FY2031 | U5: FY2032 | V5: x | W5: FY2027 | X5: FY2028 | Y5: FY2029 | Z5: FY2030 | AA5: FY2031 | AB5: FY2032
B6: DGrid chipset die (B2B) | C6: Combined | D6: Silicon | E6: Chipsets | F6: Licence / OEM Supply | G6: FY2028 | I6: =IFERROR(P6*W6,"")/10^7 -> 0 | J6: =IFERROR(Q6*X6,"")/10^7 -> 0.054 | K6: =IFERROR(R6*Y6,"")/10^7 -> 3.15 | L6: =IFERROR(S6*Z6,"")/10^7 -> 10.8 | M6: =IFERROR(T6*AA6,"")/10^7 -> 27 | N6: =IFERROR(U6*AB6,"")/10^7 -> 54 | P6: 0 | Q6: 30 | R6: 1750 | S6: 6000 | T6: 15000 | U6: 30000 | W6: 18000 | X6: 18000 | Y6: 18000 | Z6: 18000 | AA6: 18000 | AB6: 18000
B7: S100 / SDV die | C7: S100 | D7: Silicon | E7: Chipsets | F7: Licence / OEM Supply | G7: FY2028 | I7: =IFERROR(P7*W7,"")/10^7 -> 0 | J7: =IFERROR(Q7*X7,"")/10^7 -> 0.225 | K7: =IFERROR(R7*Y7,"")/10^7 -> 0.45 | L7: =IFERROR(S7*Z7,"")/10^7 -> 0.9 | M7: =IFERROR(T7*AA7,"")/10^7 -> 4.5 | N7: =IFERROR(U7*AB7,"")/10^7 -> 13.5 | P7: 0 | Q7: 50 | R7: 100 | S7: 200 | T7: 1000 | U7: 3000 | W7: 45000 | X7: 45000 | Y7: 45000 | Z7: 45000 | AA7: 45000 | AB7: 45000
B8: R100 radar-processor die | C8: R100 | D8: Silicon | E8: Chipsets | F8: Licence / OEM Supply | G8: FY2028 | I8: =IFERROR(P8*W8,"")/10^7 -> 0 | J8: =IFERROR(Q8*X8,"")/10^7 -> 0.075 | K8: =IFERROR(R8*Y8,"")/10^7 -> 0.15 | L8: =IFERROR(S8*Z8,"")/10^7 -> 0.3 | M8: =IFERROR(T8*AA8,"")/10^7 -> 1.5 | N8: =IFERROR(U8*AB8,"")/10^7 -> 7.5 | P8: 0 | Q8: 50 | R8: 100 | S8: 200 | T8: 1000 | U8: 5000 | W8: 15000 | X8: 15000 | Y8: 15000 | Z8: 15000 | AA8: 15000 | AB8: 15000
B9: 4D radar pod | C9: R100 | D9: Sensors | E9: Sensor Modules | F9: Product Sales | G9: FY2027 | I9: =IFERROR(P9*W9,"")/10^7 -> 0.075 | J9: =IFERROR(Q9*X9,"")/10^7 -> 0.3 | K9: =IFERROR(R9*Y9,"")/10^7 -> 0.875 | L9: =IFERROR(S9*Z9,"")/10^7 -> 2 | M9: =IFERROR(T9*AA9,"")/10^7 -> 4 | N9: =IFERROR(U9*AB9,"")/10^7 -> 7.5 | P9: 30 | Q9: 120 | R9: 350 | S9: 800 | T9: 1600 | U9: 3000 | W9: 25000 | X9: 25000 | Y9: 25000 | Z9: 25000 | AA9: 25000 | AB9: 25000
B10: Thermal camera | C10: T100 | D10: Sensors | E10: Sensor Modules | F10: Product Sales | G10: FY2027 | I10: =IFERROR(P10*W10,"")/10^7 -> 0.2 | J10: =IFERROR(Q10*X10,"")/10^7 -> 0.75 | K10: =IFERROR(R10*Y10,"")/10^7 -> 2 | L10: =IFERROR(S10*Z10,"")/10^7 -> 4.5 | M10: =IFERROR(T10*AA10,"")/10^7 -> 9 | N10: =IFERROR(U10*AB10,"")/10^7 -> 16 | P10: 40 | Q10: 150 | R10: 400 | S10: 900 | T10: 1800 | U10: 3200 | W10: 50000 | X10: 50000 | Y10: 50000 | Z10: 50000 | AA10: 50000 | AB10: 50000
B11: H100 driver-monitor (DMS) | C11: H100 | D11: Sensors | E11: Sensor Modules | F11: Product Sales | G11: FY2027 | I11: =IFERROR(P11*W11,"")/10^7 -> 0.1 | J11: =IFERROR(Q11*X11,"")/10^7 -> 0.4 | K11: =IFERROR(R11*Y11,"")/10^7 -> 1.1 | L11: =IFERROR(S11*Z11,"")/10^7 -> 2.5 | M11: =IFERROR(T11*AA11,"")/10^7 -> 5.5 | N11: =IFERROR(U11*AB11,"")/10^7 -> 10 | P11: 200 | Q11: 800 | R11: 2200 | S11: 5000 | T11: 11000 | U11: 20000 | W11: 5000 | X11: 5000 | Y11: 5000 | Z11: 5000 | AA11: 5000 | AB11: 5000
B12: AD1 Indoor Autonomy Stack | C12: A100 | D12: Systems | E12: Robotics Systems | F12: Product Sales | G12: FY2027 | I12: =IFERROR(P12*W12,"")/10^7 -> 0.08 | J12: =IFERROR(Q12*X12,"")/10^7 -> 0.2 | K12: =IFERROR(R12*Y12,"")/10^7 -> 4 | L12: =IFERROR(S12*Z12,"")/10^7 -> 10 | M12: =IFERROR(T12*AA12,"")/10^7 -> 22 | N12: =IFERROR(U12*AB12,"")/10^7 -> 42 | P12: 8 | Q12: 20 | R12: 400 | S12: 1000 | T12: 2200 | U12: 4200 | W12: 100000 | X12: 100000 | Y12: 100000 | Z12: 100000 | AA12: 100000 | AB12: 100000
B13: AD0 Smart Mirror (360) | C13: A100 | D13: Systems | E13: Mobility Systems | F13: Product Sales | G13: FY2027 | I13: =IFERROR(P13*W13,"")/10^7 -> 0.05 | J13: =IFERROR(Q13*X13,"")/10^7 -> 11 | K13: =IFERROR(R13*Y13,"")/10^7 -> 40 | L13: =IFERROR(S13*Z13,"")/10^7 -> 90 | M13: =IFERROR(T13*AA13,"")/10^7 -> 170 | N13: =IFERROR(U13*AB13,"")/10^7 -> 270 | P13: 10 | Q13: 2200 | R13: 8000 | S13: 18000 | T13: 34000 | U13: 54000 | W13: 50000 | X13: 50000 | Y13: 50000 | Z13: 50000 | AA13: 50000 | AB13: 50000
B14: AD2 Truck ADAS kit (compute+SW+sensors) | C14: A100 | D14: Systems | E14: Mobility Systems | F14: Product Sales | G14: FY2027 | I14: =IFERROR(P14*W14,"")/10^7 -> 2.5 | J14: =IFERROR(Q14*X14,"")/10^7 -> 6.25 | K14: =IFERROR(R14*Y14,"")/10^7 -> 35 | L14: =IFERROR(S14*Z14,"")/10^7 -> 100 | M14: =IFERROR(T14*AA14,"")/10^7 -> 225 | N14: =IFERROR(U14*AB14,"")/10^7 -> 450 | P14: 100 | Q14: 250 | R14: 1400 | S14: 4000 | T14: 9000 | U14: 18000 | W14: 250000 | X14: 250000 | Y14: 250000 | Z14: 250000 | AA14: 250000 | AB14: 250000
B15: AD3 Autonomous TaaS (fleet rental) | C15: A100 | D15: Systems | E15: Mobility Systems | F15: Rental / TaaS | G15: FY2028 | I15: =IFERROR(P15*W15,"")/10^7 -> 0 | J15: =IFERROR(Q15*X15,"")/10^7 -> 3.3 | K15: =IFERROR(R15*Y15,"")/10^7 -> 6.6 | L15: =IFERROR(S15*Z15,"")/10^7 -> 16.5 | M15: =IFERROR(T15*AA15,"")/10^7 -> 33 | N15: =IFERROR(U15*AB15,"")/10^7 -> 66 | P15: 0 | Q15: 5 | R15: 10 | S15: 25 | T15: 50 | U15: 100 | W15: 6600000 | X15: 6600000 | Y15: 6600000 | Z15: 6600000 | AA15: 6600000 | AB15: 6600000
B16: AD1 - AMR Autonomous Mobile Robot (up to 100kg) | C16: A100 | D16: Systems | E16: Robotics Systems | F16: Product Sales | G16: FY2027 | I16: =IFERROR(P16*W16,"")/10^7 -> 0.06 | J16: =IFERROR(Q16*X16,"")/10^7 -> 0.6 | K16: =IFERROR(R16*Y16,"")/10^7 -> 1.5 | L16: =IFERROR(S16*Z16,"")/10^7 -> 3 | M16: =IFERROR(T16*AA16,"")/10^7 -> 6 | N16: =IFERROR(U16*AB16,"")/10^7 -> 12 | P16: 1 | Q16: 10 | R16: 25 | S16: 50 | T16: 100 | U16: 200 | W16: 600000 | X16: 600000 | Y16: 600000 | Z16: 600000 | AA16: 600000 | AB16: 600000
B17: AD4 Seaport AGV | C17: A100 | D17: Systems | E17: Mobility Systems | F17: Product Sales | G17: FY2028 | I17: =IFERROR(P17*W17,"")/10^7 -> 0 | J17: =IFERROR(Q17*X17,"")/10^7 -> 0.906 | K17: =IFERROR(R17*Y17,"")/10^7 -> 2.265 | L17: =IFERROR(S17*Z17,"")/10^7 -> 4.53 | M17: =IFERROR(T17*AA17,"")/10^7 -> 6.795 | N17: =IFERROR(U17*AB17,"")/10^7 -> 22.65 | P17: 0 | Q17: 2 | R17: 5 | S17: 10 | T17: 15 | U17: 50 | W17: 4530000 | X17: 4530000 | Y17: 4530000 | Z17: 4530000 | AA17: 4530000 | AB17: 4530000
... B31: DGrid AI Software licence (SaaS) | C31: T100 | D31: Sentience | E31: AI Software / SaaS | F31: SaaS Subscription | G31: FY2029 | I31: =IFERROR(P31*W31,"")/10^7 -> 0 | J31: =IFERROR(Q31*X31,"")/10^7 -> 0 | K31: =IFERROR(R31*Y31,"")/10^7 -> 2 | L31: =IFERROR(S31*Z31,"")/10^7 -> 6 | M31: =IFERROR(T31*AA31,"")/10^7 -> 18 | N31: =IFERROR(U31*AB31,"")/10^7 -> 50 | P31: 0 | Q31: 0 | R31: 2 | S31: 6 | T31: 18 | U31: 50 | W31: 10000000 | X31: 10000000 | Y31: 10000000 | Z31: 10000000 | AA31: 10000000 | AB31: 10000000
B34: Total | I34: =SUBTOTAL(9,I6:I32) -> 5.995 | J34: =SUBTOTAL(9,J6:J32) -> 41.166 | K34: =SUBTOTAL(9,K6:K32) -> 144.7275 | L34: =SUBTOTAL(9,L6:L32) -> 351.355 | M34: =SUBTOTAL(9,M6:M32) -> 731.545 | N34: =SUBTOTAL(9,N6:N32) -> 1387.95 | P34: =SUBTOTAL(9,P6:P32) -> 404 | Q34: =SUBTOTAL(9,Q6:Q32) -> 4117 | R34: =SUBTOTAL(9,R6:R32) -> 15688 | S34: =SUBTOTAL(9,S6:S32) -> 38144 | T34: =SUBTOTAL(9,T6:T32) -> 80666 | U34: =SUBTOTAL(9,U6:U32) -> 148275

Sheet Tapeout Expenses
B2: DeepGrid Semi Private Limited
B3: Modelling Assumptions
B5: A. PHASED TAPEOUT PROGRAM
B6: Line Item | C6: x | D6: $ | E6: Rs. Cr | F6: x | G6: Comment
B7: A100 block MPW (5mm2 x $13,800/mm2, 100 samples) | D7: 69000 | E7: =D7*Assumptions!$D$5/10^7 -> 0.6486 | G7: muSemi shared block, TSMC 28nm; compute block
B8: R100 block MPW (5mm2 x $13,800/mm2, 100 samples) | D8: 69000 | E8: =D8*Assumptions!$D$5/10^7 -> 0.6486 | G8: muSemi shared block; radar DSP block
B9: Full 57mm2 MPW prototype (1p8m 8-metal) | D9: 232000 | E9: =D9*Assumptions!$D$5/10^7 -> 2.1808 | G9: muSemi full block $220k + 5 proto wafers @ $2,400
B10: SmartSoC backend -> GDSII (PD / DFT / integration / signoff) | D10: 1000000 | E10: =D10*Assumptions!$D$5/10^7 -> 9.4 | G10: After MPW blocks proven
B11: Dedicated mask set (TSMC 28nm 1p8m, negotiable) | D11: 1000000 | E11: =D11*Assumptions!$D$5/10^7 -> 9.4 | G11: Full production mask, separate foundry cost
B12: IP — PrimeSoC MIPI + PCIe4 + LPDDR5X | D12: 300000 | E12: =D12*Assumptions!$D$5/10^7 -> 2.82 | G12: Controller IP bundle (one-time licence)
B13: IP — Terminus Circuits PHY | D13: 500000 | E13: =D13*Assumptions!$D$5/10^7 -> 4.7 | G13: PHY IP; $400-600k negotiable, midpoint
B15: Total program NRE (one-time) | D15: =SUM(D7:D13) -> 3170000 | E15: =SUM(E7:E13) -> 29.798 | G15: ~$3.2M total; validate A100/R100 blocks on MPW, then full die, then dedicated mask
B17: B. PER-DIE COST AT VOLUME (derived from die size + yield)
B18: Overheads | C18: x | D18: Item | E18: x | G18: Comment
B19: SoC2 die area (mm2) | D19: 57 | G19: v7 single-die SoC2, TSMC 28nm HPC+
B20: Wafer diameter (mm) | D20: 300 | G20: Standard 300mm wafer
B21: Gross die per wafer (edge-corrected) | D21: =ROUND(PI()*((D20/2-3)^2)/D19-PI()*(D20-6)/SQRT(D19),0) -> 1069 | G21: GDPW formula: pi*r^2/A - pi*2r/sqrt(A)
B22: Yield (mature 28nm) | D22: 0.945 | G22: Murphy model at ~0.1/cm2 defect density
B23: Good die per wafer | D23: =ROUND(D21*D22,0) -> 1010 | G23: Gross die x yield
B24: 28nm wafer cost ($/wafer) | D24: 2400 | G24: Volume-committed price (~500k dies); TSMC 28nm
B25: Wafer cost per die ($) | D25: =D24/D23 -> 2.3762376 | G25: Wafer cost / good die
B26: Assembly, test & packaging ($) | D26: 1.5 | G26: OSAT / QuikPak at volume
B27: Per-die cost at volume ($) | D27: =SUM(D25:D26) -> 3.8762376 | G27: Wafer/die + ATP
B29: Incumbent ADAS SoC cost ($) | D29: 3000 | G29: Mobileye/Nvidia class: $3,000-8,000
B30: Cost advantage vs incumbent (x) | D30: =D29/D27 -> 773.94636
B32: C. NRE BREAKEVEN
B33: Chip contribution inside a kit ($/chip) | D33: 22 | G33: ASIC replaces Rs65k FPGA module; priced inside kit BOM
B34: Gross margin per chip ($) | D34: =D33-D27 -> 18.123762
B35: Breakeven volume (chips to recover NRE) | D35: =ROUND(D15/D34,0) -> 174908 | G35: Total NRE / gross margin per chip
B37: D. SoC4 5nm SLIP SENSITIVITY
B38: Silicon & Compute revenue FY32 (on-time) | D38: ='Sales Summary'!I20+'Sales Summary'!I16 -> 185.3 | G38: From Sales Summary
B39: Haircut if SoC4 tapes out 12 months late | D39: 0.3
B40: Silicon & Compute revenue FY32 (slip case) | D40: =D38*(1-D39) -> 129.71 | G40: ~Rs56 Cr lost; chip+box ramp pushed one year right
B42: E. BEYOND FY32 — THE NEXT GROWTH WAVE
B43: SoC4 5nm is the option on the next two markets, both arriving post-FY32:
B44: 1. Robotaxi / L4 on Indian roads — SoC4 is the compute to win it; the company are chip-ready when the market arrives.
B45: 2. Datacenter-class chipset — a bigger bet: the same transformer-native architecture scaled to datacenter inference.
B46: The Rs300 Cr cumulative R&D (FY28-32) is not a cost centre — it funds these two options from operating profit, so the
B47: FY33+ growth wave needs no new external capital for silicon. This is why R&D runs high by design.

Sheet Payroll
B2: DeepGrid Semi Private Limited
B3: Payroll Projections
D4: Headcount | K4: Monthly Gross | R4: Yearly Gross | Y4: Total Payroll Cost
B5: Department | C5: x | D5: FY2027 | E5: FY2028 | F5: FY2029 | G5: FY2030 | H5: FY2031 | I5: FY2032 | J5: x | K5: FY2027 | L5: FY2028 | M5: FY2029 | N5: FY2030 | O5: FY2031 | P5: FY2032 | Q5: x | R5: FY2027 | S5: FY2028 | T5: FY2029 | U5: FY2030 | V5: FY2031 | W5: FY2032 | X5: x | Y5: FY2027 | Z5: FY2028 | AA5: FY2029 | AB5: FY2030 | AC5: FY2031 | AD5: FY2032
B6: Management | D6: 3 | E6: 4 | F6: 4 | G6: 6 | H6: 6 | I6: 8 | K6: 222750 | L6: 272250 | M6: 299475 | N6: 329422.5 | O6: 362364.75 | P6: 398601.23 | R6: =K6*12 -> 2673000 | S6: =L6*12 -> 3267000 | T6: =M6*12 -> 3593700 | U6: =N6*12 -> 3953070 | V6: =O6*12 -> 4348377 | W6: =P6*12 -> 4783214.7 | Y6: =(D6*R6)/10^7 -> 0.8019 | Z6: =(E6*S6)/10^7 -> 1.3068 | AA6: =(F6*T6)/10^7 -> 1.43748 | AB6: =(G6*U6)/10^7 -> 2.371842 | AC6: =(H6*V6)/10^7 -> 2.6090262 | AD6: =(I6*W6)/10^7 -> 3.8265718
B7: AI | D7: 4 | E7: 10 | F7: 20 | G7: 25 | H7: 44 | I7: 68 | K7: 66659.67 | L7: 81472.93 | M7: 89620.223 | N7: 98582.245 | O7: 108440.47 | P7: 119284.52 | R7: =K7*12 -> 799916.04 | S7: =L7*12 -> 977675.16 | T7: =M7*12 -> 1075442.7 | U7: =N7*12 -> 1182986.9 | V7: =O7*12 -> 1301285.6 | W7: =P7*12 -> 1431414.2 | Y7: =(D7*R7)/10^7 -> 0.31996642 | Z7: =(E7*S7)/10^7 -> 0.97767516 | AA7: =(F7*T7)/10^7 -> 2.1508854 | AB7: =(G7*U7)/10^7 -> 2.9574674 | AC7: =(H7*V7)/10^7 -> 5.7256568 | AD7: =(I7*W7)/10^7 -> 9.7336166
B8: Design | D8: 2 | E8: 4 | F8: 4 | G8: 6 | H8: 10 | I8: 18 | K8: 37620 | L8: 45980 | M8: 50578 | N8: 55635.8 | O8: 61199.38 | P8: 67319.318 | R8: =K8*12 -> 451440 | S8: =L8*12 -> 551760 | T8: =M8*12 -> 606936 | U8: =N8*12 -> 667629.6 | V8: =O8*12 -> 734392.56 | W8: =P8*12 -> 807831.82 | Y8: =(D8*R8)/10^7 -> 0.090288 | Z8: =(E8*S8)/10^7 -> 0.220704 | AA8: =(F8*T8)/10^7 -> 0.2427744 | AB8: =(G8*U8)/10^7 -> 0.40057776 | AC8: =(H8*V8)/10^7 -> 0.73439256 | AD8: =(I8*W8)/10^7 -> 1.4540973
B9: Firmware | D9: 3 | E9: 6 | F9: 10 | G9: 12 | H9: 19 | I9: 38 | K9: 34650 | L9: 42350 | M9: 46585 | N9: 51243.5 | O9: 56367.85 | P9: 62004.635 | R9: =K9*12 -> 415800 | S9: =L9*12 -> 508200 | T9: =M9*12 -> 559020 | U9: =N9*12 -> 614922 | V9: =O9*12 -> 676414.2 | W9: =P9*12 -> 744055.62 | Y9: =(D9*R9)/10^7 -> 0.12474 | Z9: =(E9*S9)/10^7 -> 0.30492 | AA9: =(F9*T9)/10^7 -> 0.55902 | AB9: =(G9*U9)/10^7 -> 0.7379064 | AC9: =(H9*V9)/10^7 -> 1.285187 | AD9: =(I9*W9)/10^7 -> 2.8274114
B10: Hardware | D10: 6 | E10: 15 | F10: 30 | G10: 35 | H10: 57 | I10: 98 | K10: 57600.18 | L10: 70400.22 | M10: 77440.242 | N10: 85184.266 | O10: 93702.693 | P10: 103072.96 | R10: =K10*12 -> 691202.16 | S10: =L10*12 -> 844802.64 | T10: =M10*12 -> 929282.9 | U10: =N10*12 -> 1022211.2 | V10: =O10*12 -> 1124432.3 | W10: =P10*12 -> 1236875.5 | Y10: =(D10*R10)/10^7 -> 0.4147213 | Z10: =(E10*S10)/10^7 -> 1.267204 | AA10: =(F10*T10)/10^7 -> 2.7878487 | AB10: =(G10*U10)/10^7 -> 3.5777392 | AC10: =(H10*V10)/10^7 -> 6.4092642 | AD10: =(I10*W10)/10^7 -> 12.12138
B11: HR | D11: 2 | E11: 4 | F11: 5 | G11: 6 | H11: 9 | I11: 23 | K11: 12375 | L11: 15125 | M11: 16637.5 | N11: 18301.25 | O11: 20131.375 | P11: 22144.513 | R11: =K11*12 -> 148500 | S11: =L11*12 -> 181500 | T11: =M11*12 -> 199650 | U11: =N11*12 -> 219615 | V11: =O11*12 -> 241576.5 | W11: =P11*12 -> 265734.15 | Y11: =(D11*R11)/10^7 -> 0.0297 | Z11: =(E11*S11)/10^7 -> 0.0726 | AA11: =(F11*T11)/10^7 -> 0.099825 | AB11: =(G11*U11)/10^7 -> 0.131769 | AC11: =(H11*V11)/10^7 -> 0.21741885 | AD11: =(I11*W11)/10^7 -> 0.61118855
B12: Software | D12: 5 | E12: 12 | F12: 20 | G12: 30 | H12: 50 | I12: 105 | K12: 36029.07 | L12: 44035.53 | M12: 48439.083 | N12: 53282.991 | O12: 58611.29 | P12: 64472.419 | R12: =K12*12 -> 432348.84 | S12: =L12*12 -> 528426.36 | T12: =M12*12 -> 581269 | U12: =N12*12 -> 639395.9 | V12: =O12*12 -> 703335.49 | W12: =P12*12 -> 773669.03 | Y12: =(D12*R12)/10^7 -> 0.21617442 | Z12: =(E12*S12)/10^7 -> 0.63411163 | AA12: =(F12*T12)/10^7 -> 1.162538 | AB12: =(G12*U12)/10^7 -> 1.9181877 | AC12: =(H12*V12)/10^7 -> 3.5166774 | AD12: =(I12*W12)/10^7 -> 8.1235249
B13: Testing | D13: 2 | E13: 4 | F13: 6 | G13: 10 | H13: 15 | I13: 30 | K13: 9900 | L13: 12100 | M13: 13310 | N13: 14641 | O13: 16105.1 | P13: 17715.61 | R13: =K13*12 -> 118800 | S13: =L13*12 -> 145200 | T13: =M13*12 -> 159720 | U13: =N13*12 -> 175692 | V13: =O13*12 -> 193261.2 | W13: =P13*12 -> 212587.32 | Y13: =(D13*R13)/10^7 -> 0.02376 | Z13: =(E13*S13)/10^7 -> 0.05808 | AA13: =(F13*T13)/10^7 -> 0.095832 | AB13: =(G13*U13)/10^7 -> 0.175692 | AC13: =(H13*V13)/10^7 -> 0.2898918 | AD13: =(I13*W13)/10^7 -> 0.63776196
B14: Sales & BD | D14: 3 | E14: 7 | F14: 12 | G14: 20 | H14: 35 | I14: 60 | K14: 59400 | L14: 72600 | M14: 79860 | N14: 87846 | O14: 96630.6 | P14: 106293.66 | R14: 132000 | S14: 145200 | T14: 159720 | U14: 175692 | V14: 193261.2 | W14: 212587.32 | Y14: =(D14*R14)/10^7 -> 0.0396 | Z14: =(E14*S14)/10^7 -> 0.10164 | AA14: =(F14*T14)/10^7 -> 0.191664 | AB14: =(G14*U14)/10^7 -> 0.351384 | AC14: =(H14*V14)/10^7 -> 0.6764142 | AD14: =(I14*W14)/10^7 -> 1.2755239
B15: G&A / Finance | D15: 2 | E15: 5 | F15: 7 | G15: 11 | H15: 19 | I15: 33 | K15: 54450 | L15: 66550 | M15: 73205 | N15: 80525.5 | O15: 88578.05 | P15: 97435.855 | R15: 132000 | S15: 145200 | T15: 159720 | U15: 175692 | V15: 193261.2 | W15: 212587.32 | Y15: =(D15*R15)/10^7 -> 0.0264 | Z15: =(E15*S15)/10^7 -> 0.0726 | AA15: =(F15*T15)/10^7 -> 0.111804 | AB15: =(G15*U15)/10^7 -> 0.1932612 | AC15: =(H15*V15)/10^7 -> 0.36719628 | AD15: =(I15*W15)/10^7 -> 0.70153816
B16: Operations | D16: 2 | E16: 5 | F16: 10 | G16: 18 | H16: 32 | I16: 60 | K16: 44550 | L16: 54450 | M16: 59895 | N16: 65884.5 | O16: 72472.95 | P16: 79720.245 | R16: 132000 | S16: 145200 | T16: 159720 | U16: 175692 | V16: 193261.2 | W16: 212587.32 | Y16: =(D16*R16)/10^7 -> 0.0264 | Z16: =(E16*S16)/10^7 -> 0.0726 | AA16: =(F16*T16)/10^7 -> 0.15972 | AB16: =(G16*U16)/10^7 -> 0.3162456 | AC16: =(H16*V16)/10^7 -> 0.61843584 | AD16: =(I16*W16)/10^7 -> 1.2755239
B18: Total | D18: =SUM(D6:D16) -> 34 | E18: =SUM(E6:E16) -> 76 | F18: =SUM(F6:F16) -> 128 | G18: =SUM(G6:G16) -> 179 | H18: =SUM(H6:H16) -> 296 | I18: =SUM(I6:I16) -> 541 | K18: =SUM(K6:K17) -> 635983.92 | L18: =SUM(L6:L17) -> 777313.68 | M18: =SUM(M6:M17) -> 855045.05 | N18: =SUM(N6:N17) -> 940549.55 | O18: =SUM(O6:O17) -> 1034604.5 | P18: =SUM(P6:P17) -> 1138065 | R18: =SUM(R6:R17) -> 6127007 | S18: =SUM(S6:S17) -> 7440164.2 | T18: =SUM(T6:T17) -> 8184180.6 | U18: =SUM(U6:U17) -> 9002598.6 | V18: =SUM(V6:V17) -> 9902858.5 | W18: =SUM(W6:W17) -> 10893144 | Y18: =SUM(Y6:Y17) -> 2.1136501 | Z18: =SUM(Z6:Z17) -> 5.0889348 | AA18: =SUM(AA6:AA17) -> 8.9993915 | AB18: =SUM(AB6:AB17) -> 13.132072 | AC18: =SUM(AC6:AC17) -> 22.449561 | AD18: =SUM(AD6:AD17) -> 42.588139

Sheet Expense Schedules
B2: DeepGrid Semi Private Limited
B3: Expense Schedules
B5: R&D Expenses
B6: Line Item | C6: x | D6: FY2027 | E6: FY2028 | F6: FY2029 | G6: FY2030 | H6: FY2031 | I6: FY2032
B7: EDA tools & design licences | D7: 0.6 | E7: 2.75 | F7: 8.1869872 | G7: 16.53137 | H7: 28.749307 | I7: 45.096806
B8: Cloud / HPC compute for AI training | D8: 0.4 | E8: 2.0223998 | F8: 8.1869872 | G8: 17.340187 | H8: 30.764139 | I8: 48.483418
B9: Lab, prototyping & test equipment | D9: 0.33025515 | E9: 1.8615929 | F9: 7.0718807 | G9: 15.318143 | H9: 27.540409 | I9: 43.826826
B10: Total Run Rate | D10: =SUM(D7:D9) -> 1.3302551 | E10: =SUM(E7:E9) -> 6.6339927 | F10: =SUM(F7:F9) -> 23.445855 | G10: =SUM(G7:G9) -> 49.1897 | H10: =SUM(H7:H9) -> 87.053855 | I10: =SUM(I7:I9) -> 137.40705
B11: SoC4 5nm tape-out program | D11: 0.4 | E11: 6.2829607 | F11: 19.34283 | G11: 55.338412 | H11: 121.25358 | I11: 240.46234
B13: Total R&D Expenses | D13: =D10+D11 -> 1.7302551 | E13: =E10+E11 -> 12.916953 | F13: =F10+F11 -> 42.788685 | G13: =G10+G11 -> 104.52811 | H13: =H10+H11 -> 208.30744 | I13: =I10+I11 -> 377.86939
B15: G&A Expenses
B16: Line Item | C16: x | D16: FY2027 | E16: FY2028 | F16: FY2029 | G16: FY2030 | H16: FY2031 | I16: FY2032
B17: Facilities & rent (T-Hub + expansion) | D17: 0.19983333 | E17: 1.2393285 | F17: 4.1133079 | G17: 8.994688 | H17: 19.383613 | I17: 33.563155
B18: Legal, IP & compliance | D18: 0.1199 | E18: 0.82621901 | F18: 2.7422053 | G18: 5.62168 | H18: 11.182854 | I18: 17.664818
B19: Audit & professional fees | D19: 0.079933333 | E19: 0.49573141 | F19: 1.5996197 | G19: 3.373008 | H19: 6.7097121 | I19: 10.598891
B20: Insurance (D&O, liability, product) | D20: 0.05995 | E20: 0.41310951 | F20: 1.3711026 | G20: 3.091924 | H20: 6.3369503 | I20: 10.598891
B21: IT, software & subscriptions (non-R&D) | D21: 0.079933333 | E21: 0.49573141 | F21: 1.5996197 | G21: 3.373008 | H21: 7.0824739 | I21: 11.482132
B22: Travel & other admin | D22: 0.05995 | E22: 0.44065014 | F22: 1.5996197 | G22: 3.654092 | H22: 7.8279975 | I22: 13.248614
B24: Total | D24: =SUM(D17:D22) -> 0.5995 | E24: =SUM(E17:E22) -> 3.91077 | F24: =SUM(F17:F22) -> 13.025475 | G24: =SUM(G17:G22) -> 28.1084 | H24: =SUM(H17:H22) -> 58.5236 | I24: =SUM(I17:I22) -> 97.1565
B26: Sales and Marketing Expenses
B27: Line Item | C27: x | D27: FY2027 | E27: FY2028 | F27: FY2029 | G27: FY2030 | H27: FY2031 | I27: FY2032
B28: Digital marketing & demand generation | D28: 0.1 | E28: 1.170582 | F28: 4.0140372 | G28: 9.4163082 | H28: 18.884887 | I28: 34.443645
B29: Field pilots, demos & evaluation units | D29: 0.2 | E29: 1.755873 | F29: 6.0210558 | G29: 14.124462 | H29: 28.327331 | I29: 51.665468
B30: Channel & partner commissions | D30: 0.1 | E30: 1.4632275 | F30: 5.0175465 | G30: 11.770385 | H30: 23.606109 | I30: 43.054557
B31: Trade shows, events & branding | D31: 0.08 | E31: 0.7023492 | F31: 2.4084223 | G31: 5.6497849 | H31: 11.330932 | I31: 20.666187
B32: Customer success & field support | D32: 0.08 | E32: 0.7608783 | F32: 2.6091242 | G32: 6.1206003 | H32: 12.275177 | I32: 22.388369
B34: Total | D34: =SUM(D28:D32) -> 0.56 | E34: =SUM(E28:E32) -> 5.85291 | F34: =SUM(F28:F32) -> 20.070186 | G34: =SUM(G28:G32) -> 47.081541 | H34: =SUM(H28:H32) -> 94.424436 | I34: =SUM(I28:I32) -> 172.21823
